pureskillgg_makenew_pyskill/__init__.py
pureskillgg_makenew_pyskill/env_functions/env_setup.py
pureskillgg_makenew_pyskill/notebook/__init__.py
pureskillgg_makenew_pyskill/notebook/setup_notebook.py
pureskillgg_makenew_pyskill/todo.py
pureskillgg_makenew_pyskill/todo_test.py
pureskillgg_makenew_pyskill/tutorial/__init__.py
pureskillgg_makenew_pyskill/tutorial/footsteps_example.py
pureskillgg_makenew_pyskill-0.5.0.dist-info/LICENSE.txt
pureskillgg_makenew_pyskill-0.5.0.dist-info/WHEEL
pureskillgg_makenew_pyskill-0.5.0.dist-info/METADATA
pureskillgg_makenew_pyskill-0.5.0.dist-info/RECORD
